hyprpwmenu/__init__.py
hyprpwmenu/click.py
hyprpwmenu/config.py
hyprpwmenu/constants.py
hyprpwmenu/util.py
hyprpwmenu/window.py
hyprpwmenu/assets/banner.jpg
hyprpwmenu/assets/config.yaml
hyprpwmenu/assets/logoff.png
hyprpwmenu/assets/reboot.png
hyprpwmenu/assets/shutdown.png
hyprpwmenu/assets/style.css
hyprpwmenu-0.2.8.dist-info/METADATA
hyprpwmenu-0.2.8.dist-info/WHEEL
hyprpwmenu-0.2.8.dist-info/entry_points.txt
hyprpwmenu-0.2.8.dist-info/licenses/LICENSE
hyprpwmenu-0.2.8.dist-info/RECORD
