Metadata-Version: 2.4
Name: hyprpwmenu
Version: 0.2.8
Summary: A modern powermenu for Hyprland.
Project-URL: homepage, https://github.com/antrax2024/hyprpwmenu
Project-URL: Repository, https://github.com/antrax2024/hyprpwmenu
Author-email: Antrax <fredcox@gmail.com>
License: MIT
License-File: LICENSE
Requires-Python: >=3.13
Requires-Dist: confz>=2.1.0
Requires-Dist: pygobject-stubs>=2.13.0
Requires-Dist: pygobject>=3.52.3
Requires-Dist: rich>=14.0.0
